{"고한": {"hours": "22:22"}, "덕소": {"hours": "19:43"}, "도계": {"hours": "22:22"}, "동백산": {"hours": "22:22"}, "동해": {"hours": "22:22"}, "매곡": {"hours": "16:39"}, "민둥산": {"hours": "19:43"}, "봉양": {"hours": "19:43"}, "삼산": {"hours": "16:39"}, "서원주": {"hours": "19:43"}, "석불": {"hours": "16:39"}, "신기": {"hours": "16:40"}, "쌍룡": {"hours": "16:39"}, "양동": {"hours": "19:43"}, "양평": {"hours": "19:43"}, "영월": {"hours": "19:43"}, "예미": {"hours": "19:43"}, "용문": {"hours": "19:43"}, "원주": {"hours": "19:43"}, "일신": {"hours": "16:39"}, "제천": {"hours": "19:43"}, "지평": {"hours": "16:39"}, "청량리": {"hours": "19:43"}, "태백": {"hours": "22:22"}}