{"경주": {"hours": "22:04"}, "광명": {"hours": "22:45"}, "구포": {"hours": "20:16"}, "대전": {"hours": "23:09"}, "동대구": {"hours": "22:22"}, "동탄": {"hours": "19:22"}, "마산": {"hours": "19:35"}, "밀양": {"hours": "20:15"}, "부산": {"hours": "21:29"}, "서대구": {"hours": "20:16"}, "서울": {"hours": "22:45"}, "수서": {"hours": "21:27"}, "오송": {"hours": "23:52"}, "울산(통도사)": {"hours": "21:52"}, "진영": {"hours": "19:57"}, "진주": {"hours": "19:09"}, "창원": {"hours": "16:48"}, "창원중앙": {"hours": "19:47"}, "천안아산": {"hours": "23:39"}, "평택지제": {"hours": "08:33"}, "포항": {"hours": "18:59"}, "행신": {"hours": "15:48"}}