{"구미": {"hours": "20:48"}, "김천": {"hours": "20:48"}, "단양": {"hours": "19:41"}, "대구": {"hours": "20:48"}, "대전": {"hours": "19:41"}, "동대구": {"hours": "20:48"}, "부강": {"hours": "19:41"}, "삼탄": {"hours": "07:19"}, "서울": {"hours": "16:44"}, "수원": {"hours": "16:44"}, "신탄진": {"hours": "19:41"}, "안양": {"hours": "16:44"}, "영동": {"hours": "20:48"}, "영등포": {"hours": "16:44"}, "영주": {"hours": "19:41"}, "오근장": {"hours": "19:41"}, "오송": {"hours": "19:41"}, "옥천": {"hours": "19:41"}, "왜관": {"hours": "20:48"}, "음성": {"hours": "19:41"}, "이원": {"hours": "19:41"}, "전의": {"hours": "16:44"}, "제천": {"hours": "19:41"}, "조치원": {"hours": "19:41"}, "주덕": {"hours": "19:41"}, "증평": {"hours": "19:41"}, "지탄": {"hours": "07:19"}, "천안": {"hours": "16:44"}, "청주": {"hours": "19:41"}, "청주공항": {"hours": "19:41"}, "충주": {"hours": "19:41"}, "평택": {"hours": "16:44"}, "풍기": {"hours": "19:41"}, "황간": {"hours": "20:48"}}