{"강경": {"hours": "21:44"}, "광주": {"hours": "06:49"}, "광주송정": {"hours": "07:58"}, "광천": {"hours": "21:05"}, "군산": {"hours": "21:05"}, "극락강": {"hours": "06:49"}, "대야": {"hours": "18:46"}, "대천": {"hours": "21:05"}, "도고온천": {"hours": "21:05"}, "동대구": {"hours": "08:20"}, "목포": {"hours": "07:58"}, "무안": {"hours": "07:58"}, "백양사": {"hours": "07:58"}, "부산": {"hours": "08:20"}, "삽교": {"hours": "21:05"}, "서울": {"hours": "23:27"}, "서정리": {"hours": "06:49"}, "서천": {"hours": "21:05"}, "성환": {"hours": "17:25"}, "신웅천": {"hours": "21:05"}, "신태인": {"hours": "07:58"}, "영동": {"hours": "08:20"}, "예산": {"hours": "21:05"}, "옥천": {"hours": "08:20"}, "온양온천": {"hours": "21:05"}, "장항": {"hours": "21:05"}, "전의": {"hours": "17:25"}, "판교": {"hours": "21:05"}, "평택": {"hours": "21:44"}, "함평": {"hours": "07:58"}, "홍성": {"hours": "21:05"}}