{"경주": {"hours": "22:56"}, "광명": {"hours": "23:17"}, "구포": {"hours": "23:27"}, "김천구미": {"hours": "20:16"}, "대전": {"hours": "23:04"}, "동대구": {"hours": "23:14"}, "동탄": {"hours": "16:14"}, "마산": {"hours": "19:57"}, "물금": {"hours": "22:37"}, "밀양": {"hours": "21:16"}, "부산": {"hours": "22:21"}, "서울": {"hours": "22:58"}, "수서": {"hours": "17:30"}, "오송": {"hours": "23:52"}, "울산(통도사)": {"hours": "22:44"}, "진주": {"hours": "17:36"}, "창원중앙": {"hours": "18:13"}, "천안아산": {"hours": "23:39"}, "평택지제": {"hours": "08:23"}, "행신": {"hours": "14:40"}}