{"강경": {"hours": "21:06"}, "경산": {"hours": "18:42"}, "계룡": {"hours": "22:36"}, "곡성": {"hours": "20:32"}, "광주송정": {"hours": "20:14"}, "광천": {"hours": "21:59"}, "구례구": {"hours": "17:41"}, "구미": {"hours": "21:19"}, "구포": {"hours": "18:42"}, "군산": {"hours": "21:59"}, "극락강": {"hours": "17:27"}, "김제": {"hours": "21:06"}, "김천": {"hours": "21:19"}, "나주": {"hours": "20:14"}, "남성현": {"hours": "08:29"}, "남원": {"hours": "17:41"}, "논산": {"hours": "22:36"}, "대구": {"hours": "21:19"}, "대야": {"hours": "19:40"}, "대전": {"hours": "23:47"}, "동대구": {"hours": "21:19"}, "목포": {"hours": "20:14"}, "물금": {"hours": "13:29"}, "부강": {"hours": "20:52"}, "부산": {"hours": "21:19"}, "삼랑진": {"hours": "18:42"}, "삼례": {"hours": "20:32"}, "삽교": {"hours": "21:59"}, "상동": {"hours": "15:56"}, "서대전": {"hours": "22:36"}, "서울": {"hours": "23:02"}, "서정리": {"hours": "20:31"}, "서천": {"hours": "21:59"}, "성환": {"hours": "19:02"}, "수원": {"hours": "23:25"}, "순천": {"hours": "17:41"}, "신동": {"hours": "14:15"}, "신례원": {"hours": "21:59"}, "신웅천": {"hours": "21:59"}, "신탄진": {"hours": "22:36"}, "신태인": {"hours": "21:06"}, "심천": {"hours": "14:15"}, "안양": {"hours": "22:38"}, "약목": {"hours": "09:08"}, "여수EXPO": {"hours": "17:41"}, "여천": {"hours": "17:41"}, "영동": {"hours": "21:19"}, "영등포": {"hours": "23:25"}, "예산": {"hours": "21:59"}, "오근장": {"hours": "19:09"}, "오산": {"hours": "19:02"}, "오송": {"hours": "19:09"}, "옥천": {"hours": "18:42"}, "왜관": {"hours": "20:26"}, "용산": {"hours": "23:25"}, "원동": {"hours": "14:15"}, "음성": {"hours": "19:09"}, "이원": {"hours": "18:42"}, "익산": {"hours": "22:36"}, "일로": {"hours": "19:20"}, "장성": {"hours": "21:06"}, "장항": {"hours": "21:59"}, "전의": {"hours": "21:30"}, "정읍": {"hours": "21:06"}, "조치원": {"hours": "23:47"}, "주덕": {"hours": "19:09"}, "청도": {"hours": "18:42"}, "청주공항": {"hours": "19:09"}, "추풍령": {"hours": "18:42"}, "평택": {"hours": "23:25"}, "함안": {"hours": "20:26"}, "함평": {"hours": "20:14"}, "홍성": {"hours": "21:59"}, "황간": {"hours": "18:42"}}