{"경산": {"hours": "22:20"}, "광명": {"hours": "21:20"}, "광양": {"hours": "20:11"}, "광주송정": {"hours": "16:05"}, "구미": {"hours": "16:33"}, "구포": {"hours": "19:40"}, "군북": {"hours": "20:51"}, "김천": {"hours": "16:33"}, "김천구미": {"hours": "13:33"}, "나주": {"hours": "10:18"}, "남성현": {"hours": "18:45"}, "능주": {"hours": "07:35"}, "다시": {"hours": "07:35"}, "대구": {"hours": "16:33"}, "대전": {"hours": "21:49"}, "동대구": {"hours": "22:56"}, "동탄": {"hours": "17:27"}, "득량": {"hours": "07:35"}, "마산": {"hours": "22:05"}, "명봉": {"hours": "07:35"}, "목포": {"hours": "09:21"}, "몽탄": {"hours": "07:35"}, "무안": {"hours": "07:35"}, "물금": {"hours": "19:40"}, "밀양": {"hours": "23:28"}, "반성": {"hours": "20:51"}, "벌교": {"hours": "07:35"}, "보성": {"hours": "07:35"}, "부전": {"hours": "19:40"}, "북천": {"hours": "20:11"}, "사상": {"hours": "19:40"}, "삼랑진": {"hours": "19:40"}, "상동": {"hours": "18:45"}, "서광주": {"hours": "07:35"}, "서대구": {"hours": "18:14"}, "서울": {"hours": "21:20"}, "수서": {"hours": "17:27"}, "수원": {"hours": "16:33"}, "순천": {"hours": "18:25"}, "영등포": {"hours": "16:33"}, "예당": {"hours": "07:35"}, "완사": {"hours": "20:11"}, "왜관": {"hours": "09:09"}, "원동": {"hours": "19:40"}, "이양": {"hours": "07:35"}, "일로": {"hours": "07:35"}, "조성": {"hours": "07:35"}, "조치원": {"hours": "09:09"}, "중리": {"hours": "20:51"}, "진례": {"hours": "18:45"}, "진상": {"hours": "20:11"}, "진영": {"hours": "23:48"}, "진주": {"hours": "21:20"}, "창원": {"hours": "22:11"}, "천안": {"hours": "16:33"}, "천안아산": {"hours": "21:19"}, "청도": {"hours": "22:20"}, "평택": {"hours": "09:09"}, "평택지제": {"hours": "17:27"}, "하동": {"hours": "20:11"}, "한림정": {"hours": "14:57"}, "함안": {"hours": "23:59"}, "함평": {"hours": "07:35"}, "행신": {"hours": "21:20"}, "화명": {"hours": "19:40"}, "화순": {"hours": "07:35"}, "횡천": {"hours": "20:11"}, "효천": {"hours": "07:35"}}